OBP_monitoring/__init__.py
OBP_monitoring/asg_elb_healthcheck_required.py
OBP_monitoring/ec2_instance_detailed_monitoring_enabled.py
OBP_monitoring/guard_duty_enabled.py
OBP_monitoring/lambda_concurrency_check.py
OBP_monitoring/lambda_dlq_check.py
OBP_monitoring/rds_enhanced_monitoring_enabled.py
OBP_monitoring/s3_event_notifications_enabled.py
OBP_monitoring/utils.py
OBP_monitoring-0.0.1.dist-info/METADATA
OBP_monitoring-0.0.1.dist-info/WHEEL
OBP_monitoring-0.0.1.dist-info/top_level.txt
OBP_monitoring-0.0.1.dist-info/RECORD
